src/sync_count.v
////////////////////////////////////////////////////////////////////////////////
//   Module Name: sync_count.v
//  Dependencies: 25 MHz Clock, input hsync and output sync from sync count
//          Info: Module takes incoming horizontal and vertical pulses and create
//                Row and Column counters based on these syncs
//                It will align the Row/Col counters to the ouptut sync pulses
//                Useful for any module that needs to keep track of which Row/Col 
//                position we are on in the middile ofk 
////////////////////////////////////////////////////////////////////////////////


module sync_count
(
    input  i_clk,
    input  i_hsync,
    input  i_vsync,
    output reg  o_hsync,
    output reg  o_vsync,
    output reg [9:0] o_col_count = 0,
    output reg [9:0] o_row_count = 0 
);
    //Parameter Needed For producing horizontal and veritical sync
    parameter TOTAL_COLS = 800;
    parameter TOTAL_ROWS = 525;

    wire w_frame_start;

    //Registers syncs to align with the output data
    always @(posedge i_clk) begin
        o_vsync <= i_vsync;
        o_hsync <= i_hsync;
    end

    //Keep the track of Row and column counters
    always @(posedge i_clk) begin
        
        if ( w_frame_start == 1'b1) begin
            o_col_count <= 0;
            o_row_count <= 0;
        end
        else begin
            if ( o_col_count == (TOTAL_COLS - 1)) begin
                o_col_count<= 0;
                if (  o_row_count == (TOTAL_ROWS - 1) ) 
                    o_row_count<= 0;
                 else 
                    o_row_count <= o_row_count + 1;     
            end
            else begin 
                o_col_count<= o_col_count + 1;
            end
        end
    end

    //Look for rising edge on Vertical Sync to reset the counters

    assign w_frame_start = (~o_vsync & i_vsync);


endmodule

src/vga_sync_porch.v
////////////////////////////////////////////////////////////////////////////////
//   Module Name: vga_sync_porch.v
//  Dependencies: 25 MHz Clock, input hsync and vsync, also the pattern number
//          Info: Generating DIffernet Test Patterns according to the input
//                i_pattern
////////////////////////////////////////////////////////////////////////////////

module vga_sync_porch
(
    input i_clk,
    input i_hsync,
    input i_vsync,
    input [2:0] i_red_video,
    input [2:0] i_green_video,
    input [2:0] i_blue_video,
    output reg o_hsync,
    output reg o_vsync,
    output reg [2:0] o_red_video,
    output reg [2:0] o_green_video,
    output reg [2:0] o_blue_video
);

    //Parameter Needed:
    parameter VIDEO_WIDTH =    3;
    parameter TOTAL_COLS  =  800;
    parameter TOTAL_ROWS  =  525;
    parameter ACTIVE_COLS =  640;
    parameter ACTIVE_ROWS =  480;  

    parameter c_FRONT_PORCH_HORZ = 18;
    parameter c_BACK_PORCH_HORZ  = 50;
    parameter c_FRONT_PORCH_VERT = 10;
    parameter c_BACK_PORCH_VERT  = 33;

    wire w_hsync;
    wire w_vsync;
    wire [9:0] w_col_count;
    wire [9:0] w_row_count;

    reg [VIDEO_WIDTH-1:0] r_red_video = 0;
    reg [VIDEO_WIDTH-1:0] r_green_video = 0;
    reg [VIDEO_WIDTH-1:0] r_blue_video = 0;

    //Creating Instant
    sync_count i5
    (
        .i_clk(i_clk),
        .i_hsync(i_hsync),
        .i_vsync(i_vsync),
        .o_hsync(w_hsync),
        .o_vsync(w_vsync),
        .o_col_count(w_col_count),
        .o_row_count(w_row_count)
    );

    //Modifies the Hsync and Vsync signals to include Front and Back Porch
    always @(posedge i_clk) begin
        if ( (w_col_count < c_FRONT_PORCH_HORZ + ACTIVE_COLS) || (w_col_count > TOTAL_COLS - c_BACK_PORCH_HORZ) ) begin
            o_hsync <= 1'b1;
        end    
        else begin 
            o_hsync <= w_hsync;   
        end 

        if ( (w_row_count < c_FRONT_PORCH_VERT + ACTIVE_ROWS) || (w_row_count > TOTAL_ROWS - c_BACK_PORCH_VERT) ) begin
            o_vsync <= 1'b1;
        end    
        else begin 
            o_vsync <= w_vsync;   
        end 
    end

    //Align input video to modified sync pulses
    always @(posedge i_clk) begin
        r_red_video   <=   i_red_video;
        r_green_video <= i_green_video;
        r_blue_video  <=  i_blue_video;

        o_red_video   <=   r_red_video;
        o_green_video <= r_green_video;
        o_blue_video  <=  r_blue_video;
    end
endmodule

src/test_pattern_gen.v
////////////////////////////////////////////////////////////////////////////////
//   Module Name: test_pattern_gen.v
//  Dependencies: 25 MHz Clock, input hsync and vsync, also the pattern number
//          Info: Generating DIffernet Test Patterns according to the input
//                i_pattern
////////////////////////////////////////////////////////////////////////////////

/*
    Available Patterns:
    Pattern 0: Disables the test pattern generator
    Pattern 1: All Red
    Pattern 2: All Green
    Pattern 3: ALl Blue
    Pattern 4: Checkboard White/Black
*/

module test_pattern_gen
(
    input i_clk,
    input [2:0] i_pattern,
    input i_hsync,
    input i_vsync,
    output reg o_hsync = 0,
    output reg o_vsync = 0,
    output reg [2:0] o_red_video,
    output reg [2:0] o_green_video,
    output reg [2:0] o_blue_video
);

    //Parameter Needed:
    parameter VIDEO_WIDTH =    3;
    parameter TOTAL_COLS  =  800;
    parameter TOTAL_ROWS  =  525;
    parameter ACTIVE_COLS =  640;
    parameter ACTIVE_ROWS =  480;  

    //Control Signls:
    wire w_vsync;
    wire w_hsync;
    wire [9:0] w_col_count;
    wire [9:0] w_row_count;

    //Patterns have 16 indexes (0 to 15)
    wire [VIDEO_WIDTH - 1:0] pattern_red   [0:4];      //3 Bit Vector with 16 depth
    wire [VIDEO_WIDTH - 1:0] pattern_green [0:4];      //3 Bit Vector with 16 depth
    wire [VIDEO_WIDTH - 1:0] pattern_blue  [0:4];      //3 Bit Vector with 16 depth

    //Creating Instant
    sync_count i3
    (
        .i_clk(i_clk),
        .i_hsync(i_hsync),
        .i_vsync(i_vsync),
        .o_hsync(w_hsync),
        .o_vsync(w_vsync),
        .o_col_count(w_col_count),
        .o_row_count(w_row_count)
    );

    //Registers sync to align with the output data
    always @(i_clk) begin
        o_vsync <= w_vsync;
        o_hsync <= w_hsync;
    end

    // Pattern 0: Disables the Test Pattern Generator
    assign pattern_red[0]   = 0;
    assign pattern_green[0] = 0;
    assign pattern_blue[0]  = 0;

    // Pattern 1: All Red
    assign pattern_red[1]   = (w_col_count < ACTIVE_COLS && w_row_count < ACTIVE_ROWS) ? {VIDEO_WIDTH{1'b1}} : 0;
    assign pattern_green[1] = 0;
    assign pattern_blue[1]  = 0;

    // Pattern 2: All GREEN
    assign pattern_red[2]   = 0;
    assign pattern_green[2] = (w_col_count < ACTIVE_COLS && w_row_count < ACTIVE_ROWS) ? {VIDEO_WIDTH{1'b1}} : 0;
    assign pattern_blue[2]  = 0;

    // Pattern 3: All Blue
    assign pattern_red[3]   = 0;
    assign pattern_green[3] = 0;
    assign pattern_blue[3]  = (w_col_count < ACTIVE_COLS && w_row_count < ACTIVE_ROWS) ? {VIDEO_WIDTH{1'b1}} : 0;

    // Pattern 4: Checkboard White/Black
    assign pattern_red[4]   = w_col_count[5] ^ w_row_count[5] ? {VIDEO_WIDTH{1'b1}} : 0;
    assign pattern_green[4] = pattern_red[4];
    assign pattern_blue[4]  = pattern_red[4];  

    ////////////////////////////////////////////////////////////////////////////////////////////
    // Select Different Test Patterns
    ////////////////////////////////////////////////////////////////////////////////////////////
    always @(posedge i_clk) begin
        case(i_pattern)
            3'b000: begin
                o_red_video   <=   pattern_red[0];
                o_green_video <= pattern_green[0];
                o_blue_video  <=  pattern_blue[0];
            end
            3'b001: begin
                o_red_video   <=   pattern_red[1];
                o_green_video <= pattern_green[1];
                o_blue_video  <=  pattern_blue[1];
            end
            3'b010: begin
                o_red_video   <=   pattern_red[2];
                o_green_video <= pattern_green[2];
                o_blue_video  <=  pattern_blue[2];
            end
            3'b011: begin
                o_red_video   <=  pattern_red[3];
                o_green_video <= pattern_green[3];
                o_blue_video  <=  pattern_blue[3];
            end
            3'b100: begin
                o_red_video   <=  pattern_red[4];
                o_green_video <= pattern_green[4];
                o_blue_video  <=  pattern_blue[4];
            end
        endcase
    end
endmodule

src/vga_sync_pulse.v
////////////////////////////////////////////////////////////////////////////////
//   Module Name: vga_sync_pulse.v
//  Dependencies: 25 MHz Clock Input and Hsynch and Vsynch Output
//          Info: Producing Vertical and Horizontal Synch Signals using clock 
//                reference
////////////////////////////////////////////////////////////////////////////////


module vga_sync_pulse
(
    input   i_clk,
    output  o_hsync,
    output  o_vsync,
    output reg [9:0] o_col_count = 0,
    output reg [9:0] o_row_count = 0
);

    //Parameter Needed For producing horizontal and veritical sync
    parameter TOTAL_COLS = 800;
    parameter TOTAL_ROWS = 525;
    parameter ACTIVE_COLS = 640;
    parameter ACTIVE_ROWS = 480;

    always @(posedge i_clk) begin
        if( o_col_count == (TOTAL_COLS - 1))
        begin
            o_col_count<= 0;
            if (  o_row_count == (TOTAL_ROWS - 1) ) 
                o_row_count<= 0;
            else 
                o_row_count <= o_row_count + 1;     
        end    
        else begin
            o_col_count<= o_col_count + 1;
        end
    end

    assign o_hsync = o_col_count < (ACTIVE_COLS - 1) ? 1'b1 : 1'b0;
    assign o_vsync = o_row_count < (ACTIVE_ROWS - 1) ? 1'b1 : 1'b0;

endmodule

src/vga_test_pattern_top.v
////////////////////////////////////////////////////////////////////////////////
//   Module Name: vga_test_pattern_top.v
//  Dependencies: 25 MHz Clock.
//          Info: Take input a clock and produces Hsync and Vsync Control Signals
//                with 3 bit depth video out.
////////////////////////////////////////////////////////////////////////////////

`include "vga_sync_pulse.v"
`include "vga_sync_porch.v"
`include "test_pattern_gen.v"
`include  "sync_count.v"

module vga_test_pattern_top
(
    //Main Clock
    input i_clk,
    input [2:0]i_pattern,
    //VGA
    output   o_VGA_hsync,
    output   o_VGA_vsync,
    output   o_VGA_red_0,
    output   o_VGA_red_1,
    output   o_VGA_red_2,
    output o_VGA_green_0,
    output o_VGA_green_1,
    output o_VGA_green_2,
    output  o_VGA_blue_0,
    output  o_VGA_blue_1,
    output  o_VGA_blue_2
);

    //Parameter Needed:
    parameter VIDEO_WIDTH =    3;
    parameter TOTAL_COLS  =  800;
    parameter TOTAL_ROWS  =  525;
    parameter ACTIVE_COLS =  640;
    parameter ACTIVE_ROWS =  480;  
	
	//Pattern for dispaly
	//wire [2:0]i_pattern = 3'b001;

    // Common VGA Signals
    wire w_hsync_vga, wire_vsync_vga;
    wire w_hsync_tp, w_vsync_tp;
    wire w_hsync_porch, w_vsync_porch;
    wire [VIDEO_WIDTH-1:0]   w_red_TP,   w_red_Porch;
    wire [VIDEO_WIDTH-1:0] w_green_TP, w_green_Porch;
    wire [VIDEO_WIDTH-1:0]  w_blue_TP,  w_blue_Porch;

    //////////////////////////////////////////////////////////////////////////////////////
    // Creating Instants of VGA modules
    //////////////////////////////////////////////////////////////////////////////////////

    vga_sync_pulse i1
    (
        .i_clk(i_clk),
        .o_hsync(w_hsync_vga),
        .o_vsync(w_vsync_vga),
        .o_col_count(),
        .o_row_count()
    );

    test_pattern_gen i2
    (
        .i_clk(i_clk),
        .i_pattern(i_pattern),
        .i_hsync(w_hsync_vga),
        .i_vsync(w_vsync_vga),
        .o_hsync(w_hsync_tp),
        .o_vsync(w_vsync_tp),
        .o_red_video(w_red_TP),
        .o_green_video(w_green_TP),
        .o_blue_video(w_blue_TP)
    );

    vga_sync_porch i4
    (
        .i_clk(i_clk),
        .i_hsync(w_hsync_tp),
        .i_vsync(w_vsync_tp),
        .i_red_video(w_red_TP),
        .i_green_video(w_green_TP),
        .i_blue_video(w_blue_TP),
        .o_hsync(w_hsync_porch),
        .o_vsync(w_vsync_porch),
        .o_red_video(w_red_Porch),
        .o_green_video(w_green_Porch),
        .o_blue_video(w_blue_Porch)
    );

    assign   o_VGA_hsync = w_hsync_porch;
    assign   o_VGA_vsync = w_vsync_porch;

    assign   o_VGA_red_0 = w_red_Porch[0];
    assign   o_VGA_red_1 = w_red_Porch[1];
    assign   o_VGA_red_2 = w_red_Porch[2];

    assign o_VGA_green_0 = w_green_Porch[0];
    assign o_VGA_green_1 = w_green_Porch[1];
    assign o_VGA_green_2 = w_green_Porch[2];

    assign  o_VGA_blue_0 = w_blue_Porch[0];
    assign  o_VGA_blue_1 = w_blue_Porch[1];
    assign  o_VGA_blue_2 = w_blue_Porch[2]; 
endmodule

src/testbench.v
`timescale 1ns/1ns
`include "vga_test_pattern_top.v"

module testbench();

    reg clock;
    wire [2:0]i_pattern = 3'b010;

    wire   o_VGA_hsync;
    wire   o_VGA_vsync;
    wire   o_VGA_red_0;
    wire   o_VGA_red_1;
    wire   o_VGA_red_2;
    wire o_VGA_green_0;
    wire o_VGA_green_1;
    wire o_VGA_green_2;
    wire  o_VGA_blue_0;
    wire  o_VGA_blue_1;
    wire  o_VGA_blue_2;

vga_test_pattern_top i11
(
    //Main Clock
    .i_clk(clock),
    .i_pattern(i_pattern),
    //VGA
    .o_VGA_hsync(o_VGA_hsync),
    .o_VGA_vsync(o_VGA_vsync),
    .o_VGA_red_0(o_VGA_red_0),
    .o_VGA_red_1(o_VGA_red_1),
    .o_VGA_red_2(o_VGA_red_2),
    .o_VGA_green_0(o_VGA_green_0),
    .o_VGA_green_1(o_VGA_green_1),
    .o_VGA_green_2(o_VGA_green_2),
    .o_VGA_blue_0(o_VGA_blue_0),
    .o_VGA_blue_1(o_VGA_blue_1),
    .o_VGA_blue_2(o_VGA_blue_2)
);

initial
begin
    clock = 1'b0;
    forever #1 clock = ~clock;
end

initial
    $monitor($time, "clock = %b", clock);

initial
begin
    $dumpfile("a.vcd");
    $dumpvars(0, testbench);
end

initial
begin
    #5000 $finish;
end

endmodule

src/a.vcd
$date
	Tue Feb  2 01:26:26 2021
$end
$version
	Icarus Verilog
$end
$timescale
	1ns
$end
$scope module testbench $end
$var wire 3 ! i_pattern [2:0] $end
$var wire 1 " o_VGA_vsync $end
$var wire 1 # o_VGA_red_2 $end
$var wire 1 $ o_VGA_red_1 $end
$var wire 1 % o_VGA_red_0 $end
$var wire 1 & o_VGA_hsync $end
$var wire 1 ' o_VGA_green_2 $end
$var wire 1 ( o_VGA_green_1 $end
$var wire 1 ) o_VGA_green_0 $end
$var wire 1 * o_VGA_blue_2 $end
$var wire 1 + o_VGA_blue_1 $end
$var wire 1 , o_VGA_blue_0 $end
$var reg 1 - clock $end
$scope module i11 $end
$var wire 1 - i_clk $end
$var wire 3 . i_pattern [2:0] $end
$var wire 1 & o_VGA_hsync $end
$var wire 1 " o_VGA_vsync $end
$var wire 1 / w_vsync_vga $end
$var wire 1 0 w_vsync_tp $end
$var wire 1 1 w_vsync_porch $end
$var wire 3 2 w_red_TP [2:0] $end
$var wire 3 3 w_red_Porch [2:0] $end
$var wire 1 4 w_hsync_vga $end
$var wire 1 5 w_hsync_tp $end
$var wire 1 6 w_hsync_porch $end
$var wire 3 7 w_green_TP [2:0] $end
$var wire 3 8 w_green_Porch [2:0] $end
$var wire 3 9 w_blue_TP [2:0] $end
$var wire 3 : w_blue_Porch [2:0] $end
$var wire 1 # o_VGA_red_2 $end
$var wire 1 $ o_VGA_red_1 $end
$var wire 1 % o_VGA_red_0 $end
$var wire 1 ' o_VGA_green_2 $end
$var wire 1 ( o_VGA_green_1 $end
$var wire 1 ) o_VGA_green_0 $end
$var wire 1 * o_VGA_blue_2 $end
$var wire 1 + o_VGA_blue_1 $end
$var wire 1 , o_VGA_blue_0 $end
$scope module i1 $end
$var wire 1 - i_clk $end
$var wire 1 / o_vsync $end
$var wire 1 4 o_hsync $end
$var reg 10 ; o_col_count [9:0] $end
$var reg 10 < o_row_count [9:0] $end
$upscope $end
$scope module i2 $end
$var wire 1 - i_clk $end
$var wire 1 4 i_hsync $end
$var wire 3 = i_pattern [2:0] $end
$var wire 1 / i_vsync $end
$var wire 1 > w_vsync $end
$var wire 10 ? w_row_count [9:0] $end
$var wire 1 @ w_hsync $end
$var wire 10 A w_col_count [9:0] $end
$var reg 3 B o_blue_video [2:0] $end
$var reg 3 C o_green_video [2:0] $end
$var reg 1 5 o_hsync $end
$var reg 3 D o_red_video [2:0] $end
$var reg 1 0 o_vsync $end
$scope module i3 $end
$var wire 1 - i_clk $end
$var wire 1 4 i_hsync $end
$var wire 1 / i_vsync $end
$var wire 1 E w_frame_start $end
$var reg 10 F o_col_count [9:0] $end
$var reg 1 @ o_hsync $end
$var reg 10 G o_row_count [9:0] $end
$var reg 1 > o_vsync $end
$upscope $end
$upscope $end
$scope module i4 $end
$var wire 3 H i_blue_video [2:0] $end
$var wire 1 - i_clk $end
$var wire 3 I i_green_video [2:0] $end
$var wire 1 5 i_hsync $end
$var wire 3 J i_red_video [2:0] $end
$var wire 1 0 i_vsync $end
$var wire 1 K w_vsync $end
$var wire 10 L w_row_count [9:0] $end
$var wire 1 M w_hsync $end
$var wire 10 N w_col_count [9:0] $end
$var reg 3 O o_blue_video [2:0] $end
$var reg 3 P o_green_video [2:0] $end
$var reg 1 6 o_hsync $end
$var reg 3 Q o_red_video [2:0] $end
$var reg 1 1 o_vsync $end
$var reg 3 R r_blue_video [2:0] $end
$var reg 3 S r_green_video [2:0] $end
$var reg 3 T r_red_video [2:0] $end
$scope module i5 $end
$var wire 1 - i_clk $end
$var wire 1 5 i_hsync $end
$var wire 1 0 i_vsync $end
$var wire 1 U w_frame_start $end
$var reg 10 V o_col_count [9:0] $end
$var reg 1 M o_hsync $end
$var reg 10 W o_row_count [9:0] $end
$var reg 1 K o_vsync $end
$upscope $end
$upscope $end
$upscope $end
$upscope $end
$enddefinitions $end
#0
$dumpvars
b0 W
b0 V
xU
b0 T
b0 S
b0 R
bx Q
bx P
bx O
b0 N
xM
b0 L
xK
bx J
bx I
bx H
b0 G
b0 F
xE
bx D
bx C
bx B
b0 A
x@
b0 ?
x>
b10 =
b0 <
b0 ;
bx :
bx 9
bx 8
bx 7
x6
x5
14
bx 3
bx 2
x1
x0
1/
b10 .
0-
x,
x+
x*
x)
x(
x'
x&
x%
x$
x#
x"
b10 !
$end
#1
0E
0*
0+
0,
0'
0(
0)
0#
0$
0%
b1 ;
1@
1>
b1 A
b1 F
b0 9
b0 B
b0 H
b111 7
b111 C
b111 I
b0 2
b0 D
b0 J
b1 N
b1 V
1"
11
1&
16
b0 :
b0 O
b0 8
b0 P
b0 3
b0 Q
bx R
bx S
bx T
1-
#2
15
10
0-
#3
0U
x*
x+
x,
x'
x(
x)
x#
x$
x%
bx :
bx O
bx 8
bx P
bx 3
bx Q
b0 R
b111 S
b0 T
b10 N
b10 V
1M
1K
b10 A
b10 F
b10 ;
1-
#4
0-
#5
0*
0+
0,
1'
1(
1)
0#
0$
0%
b11 ;
b11 A
b11 F
b11 N
b11 V
b0 :
b0 O
b111 8
b111 P
b0 3
b0 Q
1-
#6
0-
#7
b100 N
b100 V
b100 A
b100 F
b100 ;
1-
#8
0-
#9
b101 ;
b101 A
b101 F
b101 N
b101 V
1-
#10
0-
#11
b110 N
b110 V
b110 A
b110 F
b110 ;
1-
#12
0-
#13
b111 ;
b111 A
b111 F
b111 N
b111 V
1-
#14
0-
#15
b1000 N
b1000 V
b1000 A
b1000 F
b1000 ;
1-
#16
0-
#17
b1001 ;
b1001 A
b1001 F
b1001 N
b1001 V
1-
#18
0-
#19
b1010 N
b1010 V
b1010 A
b1010 F
b1010 ;
1-
#20
0-
#21
b1011 ;
b1011 A
b1011 F
b1011 N
b1011 V
1-
#22
0-
#23
b1100 N
b1100 V
b1100 A
b1100 F
b1100 ;
1-
#24
0-
#25
b1101 ;
b1101 A
b1101 F
b1101 N
b1101 V
1-
#26
0-
#27
b1110 N
b1110 V
b1110 A
b1110 F
b1110 ;
1-
#28
0-
#29
b1111 ;
b1111 A
b1111 F
b1111 N
b1111 V
1-
#30
0-
#31
b10000 N
b10000 V
b10000 A
b10000 F
b10000 ;
1-
#32
0-
#33
b10001 ;
b10001 A
b10001 F
b10001 N
b10001 V
1-
#34
0-
#35
b10010 N
b10010 V
b10010 A
b10010 F
b10010 ;
1-
#36
0-
#37
b10011 ;
b10011 A
b10011 F
b10011 N
b10011 V
1-
#38
0-
#39
b10100 N
b10100 V
b10100 A
b10100 F
b10100 ;
1-
#40
0-
#41
b10101 ;
b10101 A
b10101 F
b10101 N
b10101 V
1-
#42
0-
#43
b10110 N
b10110 V
b10110 A
b10110 F
b10110 ;
1-
#44
0-
#45
b10111 ;
b10111 A
b10111 F
b10111 N
b10111 V
1-
#46
0-
#47
b11000 N
b11000 V
b11000 A
b11000 F
b11000 ;
1-
#48
0-
#49
b11001 ;
b11001 A
b11001 F
b11001 N
b11001 V
1-
#50
0-
#51
b11010 N
b11010 V
b11010 A
b11010 F
b11010 ;
1-
#52
0-
#53
b11011 ;
b11011 A
b11011 F
b11011 N
b11011 V
1-
#54
0-
#55
b11100 N
b11100 V
b11100 A
b11100 F
b11100 ;
1-
#56
0-
#57
b11101 ;
b11101 A
b11101 F
b11101 N
b11101 V
1-
#58
0-
#59
b11110 N
b11110 V
b11110 A
b11110 F
b11110 ;
1-
#60
0-
#61
b11111 ;
b11111 A
b11111 F
b11111 N
b11111 V
1-
#62
0-
#63
b100000 N
b100000 V
b100000 A
b100000 F
b100000 ;
1-
#64
0-
#65
b100001 ;
b100001 A
b100001 F
b100001 N
b100001 V
1-
#66
0-
#67
b100010 N
b100010 V
b100010 A
b100010 F
b100010 ;
1-
#68
0-
#69
b100011 ;
b100011 A
b100011 F
b100011 N
b100011 V
1-
#70
0-
#71
b100100 N
b100100 V
b100100 A
b100100 F
b100100 ;
1-
#72
0-
#73
b100101 ;
b100101 A
b100101 F
b100101 N
b100101 V
1-
#74
0-
#75
b100110 N
b100110 V
b100110 A
b100110 F
b100110 ;
1-
#76
0-
#77
b100111 ;
b100111 A
b100111 F
b100111 N
b100111 V
1-
#78
0-
#79
b101000 N
b101000 V
b101000 A
b101000 F
b101000 ;
1-
#80
0-
#81
b101001 ;
b101001 A
b101001 F
b101001 N
b101001 V
1-
#82
0-
#83
b101010 N
b101010 V
b101010 A
b101010 F
b101010 ;
1-
#84
0-
#85
b101011 ;
b101011 A
b101011 F
b101011 N
b101011 V
1-
#86
0-
#87
b101100 N
b101100 V
b101100 A
b101100 F
b101100 ;
1-
#88
0-
#89
b101101 ;
b101101 A
b101101 F
b101101 N
b101101 V
1-
#90
0-
#91
b101110 N
b101110 V
b101110 A
b101110 F
b101110 ;
1-
#92
0-
#93
b101111 ;
b101111 A
b101111 F
b101111 N
b101111 V
1-
#94
0-
#95
b110000 N
b110000 V
b110000 A
b110000 F
b110000 ;
1-
#96
0-
#97
b110001 ;
b110001 A
b110001 F
b110001 N
b110001 V
1-
#98
0-
#99
b110010 N
b110010 V
b110010 A
b110010 F
b110010 ;
1-
#100
0-
#101
b110011 ;
b110011 A
b110011 F
b110011 N
b110011 V
1-
#102
0-
#103
b110100 N
b110100 V
b110100 A
b110100 F
b110100 ;
1-
#104
0-
#105
b110101 ;
b110101 A
b110101 F
b110101 N
b110101 V
1-
#106
0-
#107
b110110 N
b110110 V
b110110 A
b110110 F
b110110 ;
1-
#108
0-
#109
b110111 ;
b110111 A
b110111 F
b110111 N
b110111 V
1-
#110
0-
#111
b111000 N
b111000 V
b111000 A
b111000 F
b111000 ;
1-
#112
0-
#113
b111001 ;
b111001 A
b111001 F
b111001 N
b111001 V
1-
#114
0-
#115
b111010 N
b111010 V
b111010 A
b111010 F
b111010 ;
1-
#116
0-
#117
b111011 ;
b111011 A
b111011 F
b111011 N
b111011 V
1-
#118
0-
#119
b111100 N
b111100 V
b111100 A
b111100 F
b111100 ;
1-
#120
0-
#121
b111101 ;
b111101 A
b111101 F
b111101 N
b111101 V
1-
#122
0-
#123
b111110 N
b111110 V
b111110 A
b111110 F
b111110 ;
1-
#124
0-
#125
b111111 ;
b111111 A
b111111 F
b111111 N
b111111 V
1-
#126
0-
#127
b1000000 N
b1000000 V
b1000000 A
b1000000 F
b1000000 ;
1-
#128
0-
#129
b1000001 ;
b1000001 A
b1000001 F
b1000001 N
b1000001 V
1-
#130
0-
#131
b1000010 N
b1000010 V
b1000010 A
b1000010 F
b1000010 ;
1-
#132
0-
#133
b1000011 ;
b1000011 A
b1000011 F
b1000011 N
b1000011 V
1-
#134
0-
#135
b1000100 N
b1000100 V
b1000100 A
b1000100 F
b1000100 ;
1-
#136
0-
#137
b1000101 ;
b1000101 A
b1000101 F
b1000101 N
b1000101 V
1-
#138
0-
#139
b1000110 N
b1000110 V
b1000110 A
b1000110 F
b1000110 ;
1-
#140
0-
#141
b1000111 ;
b1000111 A
b1000111 F
b1000111 N
b1000111 V
1-
#142
0-
#143
b1001000 N
b1001000 V
b1001000 A
b1001000 F
b1001000 ;
1-
#144
0-
#145
b1001001 ;
b1001001 A
b1001001 F
b1001001 N
b1001001 V
1-
#146
0-
#147
b1001010 N
b1001010 V
b1001010 A
b1001010 F
b1001010 ;
1-
#148
0-
#149
b1001011 ;
b1001011 A
b1001011 F
b1001011 N
b1001011 V
1-
#150
0-
#151
b1001100 N
b1001100 V
b1001100 A
b1001100 F
b1001100 ;
1-
#152
0-
#153
b1001101 ;
b1001101 A
b1001101 F
b1001101 N
b1001101 V
1-
#154
0-
#155
b1001110 N
b1001110 V
b1001110 A
b1001110 F
b1001110 ;
1-
#156
0-
#157
b1001111 ;
b1001111 A
b1001111 F
b1001111 N
b1001111 V
1-
#158
0-
#159
b1010000 N
b1010000 V
b1010000 A
b1010000 F
b1010000 ;
1-
#160
0-
#161
b1010001 ;
b1010001 A
b1010001 F
b1010001 N
b1010001 V
1-
#162
0-
#163
b1010010 N
b1010010 V
b1010010 A
b1010010 F
b1010010 ;
1-
#164
0-
#165
b1010011 ;
b1010011 A
b1010011 F
b1010011 N
b1010011 V
1-
#166
0-
#167
b1010100 N
b1010100 V
b1010100 A
b1010100 F
b1010100 ;
1-
#168
0-
#169
b1010101 ;
b1010101 A
b1010101 F
b1010101 N
b1010101 V
1-
#170
0-
#171
b1010110 N
b1010110 V
b1010110 A
b1010110 F
b1010110 ;
1-
#172
0-
#173
b1010111 ;
b1010111 A
b1010111 F
b1010111 N
b1010111 V
1-
#174
0-
#175
b1011000 N
b1011000 V
b1011000 A
b1011000 F
b1011000 ;
1-
#176
0-
#177
b1011001 ;
b1011001 A
b1011001 F
b1011001 N
b1011001 V
1-
#178
0-
#179
b1011010 N
b1011010 V
b1011010 A
b1011010 F
b1011010 ;
1-
#180
0-
#181
b1011011 ;
b1011011 A
b1011011 F
b1011011 N
b1011011 V
1-
#182
0-
#183
b1011100 N
b1011100 V
b1011100 A
b1011100 F
b1011100 ;
1-
#184
0-
#185
b1011101 ;
b1011101 A
b1011101 F
b1011101 N
b1011101 V
1-
#186
0-
#187
b1011110 N
b1011110 V
b1011110 A
b1011110 F
b1011110 ;
1-
#188
0-
#189
b1011111 ;
b1011111 A
b1011111 F
b1011111 N
b1011111 V
1-
#190
0-
#191
b1100000 N
b1100000 V
b1100000 A
b1100000 F
b1100000 ;
1-
#192
0-
#193
b1100001 ;
b1100001 A
b1100001 F
b1100001 N
b1100001 V
1-
#194
0-
#195
b1100010 N
b1100010 V
b1100010 A
b1100010 F
b1100010 ;
1-
#196
0-
#197
b1100011 ;
b1100011 A
b1100011 F
b1100011 N
b1100011 V
1-
#198
0-
#199
b1100100 N
b1100100 V
b1100100 A
b1100100 F
b1100100 ;
1-
#200
0-
#201
b1100101 ;
b1100101 A
b1100101 F
b1100101 N
b1100101 V
1-
#202
0-
#203
b1100110 N
b1100110 V
b1100110 A
b1100110 F
b1100110 ;
1-
#204
0-
#205
b1100111 ;
b1100111 A
b1100111 F
b1100111 N
b1100111 V
1-
#206
0-
#207
b1101000 N
b1101000 V
b1101000 A
b1101000 F
b1101000 ;
1-
#208
0-
#209
b1101001 ;
b1101001 A
b1101001 F
b1101001 N
b1101001 V
1-
#210
0-
#211
b1101010 N
b1101010 V
b1101010 A
b1101010 F
b1101010 ;
1-
#212
0-
#213
b1101011 ;
b1101011 A
b1101011 F
b1101011 N
b1101011 V
1-
#214
0-
#215
b1101100 N
b1101100 V
b1101100 A
b1101100 F
b1101100 ;
1-
#216
0-
#217
b1101101 ;
b1101101 A
b1101101 F
b1101101 N
b1101101 V
1-
#218
0-
#219
b1101110 N
b1101110 V
b1101110 A
b1101110 F
b1101110 ;
1-
#220
0-
#221
b1101111 ;
b1101111 A
b1101111 F
b1101111 N
b1101111 V
1-
#222
0-
#223
b1110000 N
b1110000 V
b1110000 A
b1110000 F
b1110000 ;
1-
#224
0-
#225
b1110001 ;
b1110001 A
b1110001 F
b1110001 N
b1110001 V
1-
#226
0-
#227
b1110010 N
b1110010 V
b1110010 A
b1110010 F
b1110010 ;
1-
#228
0-
#229
b1110011 ;
b1110011 A
b1110011 F
b1110011 N
b1110011 V
1-
#230
0-
#231
b1110100 N
b1110100 V
b1110100 A
b1110100 F
b1110100 ;
1-
#232
0-
#233
b1110101 ;
b1110101 A
b1110101 F
b1110101 N
b1110101 V
1-
#234
0-
#235
b1110110 N
b1110110 V
b1110110 A
b1110110 F
b1110110 ;
1-
#236
0-
#237
b1110111 ;
b1110111 A
b1110111 F
b1110111 N
b1110111 V
1-
#238
0-
#239
b1111000 N
b1111000 V
b1111000 A
b1111000 F
b1111000 ;
1-
#240
0-
#241
b1111001 ;
b1111001 A
b1111001 F
b1111001 N
b1111001 V
1-
#242
0-
#243
b1111010 N
b1111010 V
b1111010 A
b1111010 F
b1111010 ;
1-
#244
0-
#245
b1111011 ;
b1111011 A
b1111011 F
b1111011 N
b1111011 V
1-
#246
0-
#247
b1111100 N
b1111100 V
b1111100 A
b1111100 F
b1111100 ;
1-
#248
0-
#249
b1111101 ;
b1111101 A
b1111101 F
b1111101 N
b1111101 V
1-
#250
0-
#251
b1111110 N
b1111110 V
b1111110 A
b1111110 F
b1111110 ;
1-
#252
0-
#253
b1111111 ;
b1111111 A
b1111111 F
b1111111 N
b1111111 V
1-
#254
0-
#255
b10000000 N
b10000000 V
b10000000 A
b10000000 F
b10000000 ;
1-
#256
0-
#257
b10000001 ;
b10000001 A
b10000001 F
b10000001 N
b10000001 V
1-
#258
0-
#259
b10000010 N
b10000010 V
b10000010 A
b10000010 F
b10000010 ;
1-
#260
0-
